{
	"configurations" : 
	[
		{
			"directories" : 
			[
				{
					"build" : ".",
					"jsonFile" : "directory-.-Debug-d0094a50bb2071803777.json",
					"minimumCMakeVersion" : 
					{
						"string" : "3.21"
					},
					"projectIndex" : 0,
					"source" : ".",
					"targetIndexes" : 
					[
						0
					]
				}
			],
			"name" : "Debug",
			"projects" : 
			[
				{
					"directoryIndexes" : 
					[
						0
					],
					"name" : "third_practice",
					"targetIndexes" : 
					[
						0
					]
				}
			],
			"targets" : 
			[
				{
					"directoryIndex" : 0,
					"id" : "third_practice::@6890427a1f51a3e7e1df",
					"jsonFile" : "target-third_practice-Debug-5b9eb5a6e31fe67f0b65.json",
					"name" : "third_practice",
					"projectIndex" : 0
				}
			]
		}
	],
	"kind" : "codemodel",
	"paths" : 
	{
		"build" : "C:/Users/USER/Desktop/Section 1/Third section/Third exercise/cmake-build-debug",
		"source" : "C:/Users/USER/Desktop/Section 1/Third section/Third exercise"
	},
	"version" : 
	{
		"major" : 2,
		"minor" : 3
	}
}
